frattlesnake/Effect.py
frattlesnake/Familiar.py
frattlesnake/Item.py
frattlesnake/Modifier.py
frattlesnake/Range.py
frattlesnake/__init__.py
frattlesnake/frattlesnake.py
frattlesnake/kolmafia.py
frattlesnake-0.1.2.dist-info/WHEEL
frattlesnake-0.1.2.dist-info/METADATA
frattlesnake-0.1.2.dist-info/RECORD
