Metadata-Version: 2.1
Name: frattlesnake
Version: 0.1.2
Summary: frattlesnake is a bridge and library from KoLmafia's Java environment to a Python environment
Home-page: https://github.com/gausie/frattlesnake
Author: Samuel Gaus
Author-email: sam@gaus.co.uk
Requires-Python: >=3.8,<4.0
Classifier: Programming Language :: Python :: 3
Classifier: Programming Language :: Python :: 3.8
Requires-Dist: pyjnius (>=1.3.0,<2.0.0)
Project-URL: Repository, https://github.com/gausie/frattlesnake
